Tabla 1 POS/Tabla1Pos.v
//pablo muñoz 19176
module Tabla1pos();


wire OR1;
wire OR2;
wire OR3;		
wire Z1;		
wire ND1;
wire ND2;
wire ND3;		
reg A, B, C;	


not GATENA (ND1, A);		
not GATENB (ND2, B);		
not GATENC (ND3, C);		
or GATEO1 (OR1, A,B,ND3);		 
or GATEO2 (OR2, A,ND2,ND3);		
or GATEO3 (OR3, ND1,ND2,C);		
and GZ1 (Z1, OR1, OR2, OR3);	

initial begin
$display("A B C | Y");
$display("-------");

  $monitor("%b %b %b | %b", A, B, C, Z1);

  A = 0;
  B = 0;
  C = 0;

  #1 C = 1;
  #1 B = 1; C=0;
  #1 C = 1;
  #1 A=1;B=0;C=0;
  #1 C=1;
  #1 B=1;C=0;
  #1 C=1;
  #1 $finish;   
end

  initial
    begin
      $dumpfile("TablaPos1_tb.vcd"); 
      $dumpvars(0, Tabla1pos); 
    end
endmodule

Tabla 1 POS/TablaPos1_tb.vcd
$date
	Fri Jul 31 22:39:43 2020
$end
$version
	Icarus Verilog
$end
$timescale
	1ps
$end
$scope module Tabla1pos $end
$var wire 1 ! ND1 $end
$var wire 1 " ND2 $end
$var wire 1 # ND3 $end
$var wire 1 $ OR1 $end
$var wire 1 % OR2 $end
$var wire 1 & OR3 $end
$var wire 1 ' Z1 $end
$var reg 1 ( A $end
$var reg 1 ) B $end
$var reg 1 * C $end
$upscope $end
$enddefinitions $end
#0
$dumpvars
0*
0)
0(
1'
1&
1%
1$
1#
1"
1!
$end
#1
0'
0$
0#
1*
#2
1'
1#
1$
0"
0*
1)
#3
0'
0%
0#
1*
#4
1'
1#
1"
1%
0!
0*
0)
1(
#5
0#
1*
#6
0'
0&
1#
0"
0*
1)
#7
1'
1&
0#
1*
