Tabla 3 POS/Tabla3Pos.v
//pablo muñoz 19176

module Tabla3Pos();


wire OR1;
wire OR2;
wire OR3;
wire OR4;
wire OR5;
wire OR6;
wire OR7;
wire OR8;
wire OR9;		
wire ND1;		
wire NTA;
wire NTB;
wire NTC;
wire NTD;		
reg A, B, C, D;	


not GATENTA (NTA, A);		
not GATENTB (NTB, B);		
not GATENTC (NTC, C);		
not GATENTB (NTD, D);		
or GATEOR1 (OR1, A,NTB,C,D);		 
or GATEOR2 (OR2, A,NTB,C,NTD);		
or GATEOR3 (OR3, A,NTB,NTC,D);		
or GATEOR4 (OR4, A,NTB,NTC,NTD);	
or GATEOR5 (OR5, NTA,B,C,NTD);		
or GATEOR6 (OR6, NTA,B,NTC,NTD);	
or GATEOR7 (OR7, NTA,NTB,C,D);		
or GATEOR8 (OR8, NTA,NTB,C,NTD);	
or GATEOR9 (OR9, NTA,NTB,NTC,NTD);	
and GND1 (ND1, OR1, OR2, OR3, OR4, OR5, OR6, OR7, OR8, OR9);	

initial begin
$display("A B C D | ND1");
$display("-------");


  $monitor("%b %b %b %b | %b", A, B, C, D, ND1);


  A = 0;
  B = 0;
  C = 0;
  D = 0;

  #1 D=1;
  #1 C=1;D=0;
  #1 D=1;
  #1 B=1;C=0;D=0;
  #1 D=1;
  #1 C=1;D=0;
  #1 D=1;
  #1 A=1;B=0;C=0;D=0;
  #1 D=1;
  #1 C=1;D=0;
  #1 D=1;
  #1 B=1;C=0;D=0;
  #1 D=1;
  #1 C=1;D=0;
  #1 D=1;
  #1 $finish;  
end

  initial
    begin
      $dumpfile("TablaPos3_tb.vcd"); 
      $dumpvars(0, Tabla3Pos); 
    end
endmodule

Tabla 4 POS -/TablaPos3_tb.vcd
$date
	Sat Aug 01 13:12:48 2020
$end
$version
	Icarus Verilog
$end
$timescale
	1ps
$end
$scope module Tabla3Pos $end
$var wire 1 ! ND1 $end
$var wire 1 " NTA $end
$var wire 1 # NTB $end
$var wire 1 $ NTC $end
$var wire 1 % NTD $end
$var wire 1 & OR1 $end
$var wire 1 ' OR2 $end
$var wire 1 ( OR3 $end
$var wire 1 ) OR4 $end
$var wire 1 * OR5 $end
$var wire 1 + OR6 $end
$var wire 1 , OR7 $end
$var wire 1 - OR8 $end
$var wire 1 . OR9 $end
$var reg 1 / A $end
$var reg 1 0 B $end
$var reg 1 1 C $end
$var reg 1 2 D $end
$upscope $end
$enddefinitions $end
#0
$dumpvars
02
01
00
0/
1.
1-
1,
1+
1*
1)
1(
1'
1&
1%
1$
1#
1"
1!
$end
#1
0%
12
#2
1%
0$
02
11
#3
0%
12
#4
0!
1%
1'
0&
1$
0#
02
01
10
#5
0'
1&
0%
12
#6
0(
1%
1'
0$
02
11
#7
0)
1(
0%
12
#8
1!
1%
1$
1+
1*
1#
1)
0"
02
01
00
1/
#9
0!
0*
0%
12
#10
1!
1%
1*
0$
02
11
#11
0!
0+
0%
12
#12
1%
1-
0,
1$
1+
0#
02
01
10
#13
0-
1,
0%
12
#14
1!
1%
1-
0$
02
11
#15
0!
0.
0%
12
