Tabla 4 SOP/Tabla4Sop.v
//pablo muñoz 19176

module Tabla4Sop();


wire ND1;
wire ND2;
wire ND3;
wire ND4;
wire ND5;
wire ND6;
wire ND7;		
wire OR1;		
wire NT1;
wire NT2;
wire NT3;
wire NT4;		
reg A, B, C, D;	

not GNT1 (NT1, A);		
not GNT2 (NT2, B);		
not GNT3 (NT3, C);		
not GNT4 (NT4, D);		
and GND1 (ND1, NT1,NT2,NT3,NT4);	
and GND2 (ND2, NT1,NT2,C,NT4);	
and GND3 (ND3, NT1,NT2,C,D);	
and GND4 (ND4, NT1,B,C,NT4);	
and GND5 (ND5, NT1,B,C,D);		
and GND6 (ND6, A,NT2,NT3,NT4);	
and GND7 (ND7, A,NT2,C,NT4);		
or GOR1 (OR1, ND1, ND2, ND3, ND4, ND5, ND6, ND7);	

initial begin
$display("A B C D | OR1");
$display("-------");


  $monitor("%b %b %b %b | %b", A, B, C, D, OR1);


  A = 0;
  B = 0;
  C = 0;
  D = 0;

  #1 D=1;
  #1 C=1;D=0;
  #1 D=1;
  #1 B=1;C=0;D=0;
  #1 D=1;
  #1 C=1;D=0;
  #1 D=1;
  #1 A=1;B=0;C=0;D=0;
  #1 D=1;
  #1 C=1;D=0;
  #1 D=1;
  #1 B=1;C=0;D=0;
  #1 D=1;
  #1 C=1;D=0;
  #1 D=1;
  #1 $finish;  
end

  initial
    begin
      $dumpfile("TablaSop4_tb.vcd"); 
      $dumpvars(0, Tabla4Sop); 
    end
endmodule

Tabla 4 SOP/TablaSop4_tb.vcd
$date
	Sat Aug 01 16:17:30 2020
$end
$version
	Icarus Verilog
$end
$timescale
	1ps
$end
$scope module Tabla4Sop $end
$var wire 1 ! ND1 $end
$var wire 1 " ND2 $end
$var wire 1 # ND3 $end
$var wire 1 $ ND4 $end
$var wire 1 % ND5 $end
$var wire 1 & ND6 $end
$var wire 1 ' ND7 $end
$var wire 1 ( NT1 $end
$var wire 1 ) NT2 $end
$var wire 1 * NT3 $end
$var wire 1 + NT4 $end
$var wire 1 , OR1 $end
$var reg 1 - A $end
$var reg 1 . B $end
$var reg 1 / C $end
$var reg 1 0 D $end
$upscope $end
$enddefinitions $end
#0
$dumpvars
00
0/
0.
0-
1,
1+
1*
1)
1(
0'
0&
0%
0$
0#
0"
1!
$end
#1
0,
0!
0+
10
#2
1,
1"
1+
0*
00
1/
#3
0"
1#
0+
10
#4
0,
1+
0#
1*
0)
00
0/
1.
#5
0+
10
#6
1,
1$
1+
0*
00
1/
#7
0$
1%
0+
10
#8
1&
1+
1*
0%
1)
0(
00
0/
0.
1-
#9
0,
0&
0+
10
#10
1,
1'
1+
0*
00
1/
#11
0,
0'
0+
10
#12
1+
1*
0)
00
0/
1.
#13
0+
10
#14
1+
0*
00
1/
#15
0+
10
