Tabla 2 POS/Tabla2Pos.v
//PABLO MUÑOZ 19176
module Tabla2Pos();

wire OR1;
wire OR2;
wire OR3;
wire OR4;
wire OR5;		
wire ND1;		
wire NTA;
wire NTB;
wire NTC;		
reg A, B, C;	

not GATENTA (NTA, A);		
not GATENTB (NTB, B);		
not GATENTC (NTC, C);		
or GOR1 (OR1, A,B,C);		
or GOR2 (OR2, A,NTB,C);		
or GOR3 (OR3, A,NTB,NTC);		
or GOR3 (OR4, NTA,B,C);		
or GOR3 (OR5, NTA,B,NTC);		
and GA1 (ND1, OR1, OR2, OR3, OR4, OR5);	

initial begin
$display("A B C | ND1");
$display("-------");

  $monitor("%b %b %b | %b", A, B, C, ND1);


  A = 0;
  B = 0;
  C = 0;

  #1 C = 1;
  #1 B = 1; C=0;
  #1 C = 1;
  #1 A=1;B=0;C=0;
  #1 C=1;
  #1 B=1;C=0;
  #1 C=1;
  #1 $finish;   
end


  initial
    begin
      $dumpfile("TablaPos2_tb.vcd"); 
      $dumpvars(0, Tabla2Pos); 
    end
endmodule

Tabla 2 POS/TablaPos2_tb.vcd
$date
	Sat Aug 01 12:58:34 2020
$end
$version
	Icarus Verilog
$end
$timescale
	1ps
$end
$scope module Tabla2Pos $end
$var wire 1 ! ND1 $end
$var wire 1 " NTA $end
$var wire 1 # NTB $end
$var wire 1 $ NTC $end
$var wire 1 % OR1 $end
$var wire 1 & OR2 $end
$var wire 1 ' OR3 $end
$var wire 1 ( OR4 $end
$var wire 1 ) OR5 $end
$var reg 1 * A $end
$var reg 1 + B $end
$var reg 1 , C $end
$upscope $end
$enddefinitions $end
#0
$dumpvars
0,
0+
0*
1)
1(
1'
1&
0%
1$
1#
1"
0!
$end
#1
1!
1%
0$
1,
#2
0!
0&
1$
0#
0,
1+
#3
0'
1&
0$
1,
#4
1$
1)
0(
1#
1'
0"
0,
0+
1*
#5
0)
1(
0$
1,
#6
1!
1$
1)
0#
0,
1+
#7
0$
1,
