Tabla 3 SOP/Tabla3Sop.v
//pablo muñoz 19176

module Tabla3Sop 	();


wire ND1;
wire ND2;
wire ND3;
wire ND4;
wire ND5;
wire ND6;
wire ND7;		
wire OR1;		
wire NT1;
wire NT2;
wire NT3;
wire NT4;		
reg A, B, C, D;	


and GND1 (ND1, NT1,NT2,NT3,NT4);	
and GND2 (ND2, NT1,NT2,NT3,D);	
and GND3 (ND3, NT1,NT2,C,NT4);	
and GND4 (ND4, NT1,NT2,C,D);	
and GND5 (ND5, A,NT2,NT3,NT4);	
and GND6 (ND6, A,NT2,C,NT4);	
and GND7 (ND7, A,B,C,NT4);	
or  GOR1 (OR1, ND1, ND2, ND3, ND4, ND5, ND6, ND7);	
not GNTA (NT1, A);		
not GNTB (NT2, B);		
not GNTC (NT3, C);		
not GNTD (NT4, D);		

initial begin
$display("A B C D | OR1");
$display("-------");

  $monitor("%b %b %b %b | %b", A, B, C, D, OR1);


  A = 0;
  B = 0;
  C = 0;
  D = 0;

  #1 D=1;
  #1 C=1;D=0;
  #1 D=1;
  #1 B=1;C=0;D=0;
  #1 D=1;
  #1 C=1;D=0;
  #1 D=1;
  #1 A=1;B=0;C=0;D=0;
  #1 D=1;
  #1 C=1;D=0;
  #1 D=1;
  #1 B=1;C=0;D=0;
  #1 D=1;
  #1 C=1;D=0;
  #1 D=1;
  #1 $finish;   
end


  initial
    begin
      $dumpfile("TablaSop3_tb.vcd"); 
      $dumpvars(0, Tabla3Sop ); 
    end
endmodule

Tabla 3 SOP/TablaSop3_tb.vcd
$date
	Sat Aug 01 16:02:39 2020
$end
$version
	Icarus Verilog
$end
$timescale
	1ps
$end
$scope module Tabla3Sop $end
$var wire 1 ! ND1 $end
$var wire 1 " ND2 $end
$var wire 1 # ND3 $end
$var wire 1 $ ND4 $end
$var wire 1 % ND5 $end
$var wire 1 & ND6 $end
$var wire 1 ' ND7 $end
$var wire 1 ( NT1 $end
$var wire 1 ) NT2 $end
$var wire 1 * NT3 $end
$var wire 1 + NT4 $end
$var wire 1 , OR1 $end
$var reg 1 - A $end
$var reg 1 . B $end
$var reg 1 / C $end
$var reg 1 0 D $end
$upscope $end
$enddefinitions $end
#0
$dumpvars
00
0/
0.
0-
1,
1+
1*
1)
1(
0'
0&
0%
0$
0#
0"
1!
$end
#1
0!
0+
1"
10
#2
1,
1#
1+
0"
0*
00
1/
#3
0#
0+
1$
10
#4
0,
1+
1*
0$
0)
00
0/
1.
#5
0+
10
#6
1+
0*
00
1/
#7
0+
10
#8
1,
1%
1+
1*
1)
0(
00
0/
0.
1-
#9
0,
0%
0+
10
#10
1,
1&
1+
0*
00
1/
#11
0,
0&
0+
10
#12
1+
1*
0)
00
0/
1.
#13
0+
10
#14
1,
1'
1+
0*
00
1/
#15
0,
0'
0+
10
